beige/__init__.py
beige/get_alpha0.py
beige/load_data.py
beige/model.py
beret_beige-0.0.6.data/scripts/beige
beret_beige-0.0.6.dist-info/METADATA
beret_beige-0.0.6.dist-info/WHEEL
beret_beige-0.0.6.dist-info/top_level.txt
beret_beige-0.0.6.dist-info/RECORD
