Metadata-Version: 2.1
Name: beret-beige
Version: 0.0.6
Summary: Bayesian Effect size Inference with Guide counts and Editing rate
Home-page: https://github.com/jykr/beige
Author: Jayoung Ryu
Author-email: jayoung_ryu@g.harvard.edu
Classifier: Programming Language :: Python :: 3
Classifier: Operating System :: OS Independent
Requires-Dist: pyro-ppl
Requires-Dist: numpy
Requires-Dist: berets
